setup.cfg
setup.py
FreeSpeech/FreeSpeech.py
FreeSpeech/__init__.py
FreeSpeech.egg-info/PKG-INFO
FreeSpeech.egg-info/SOURCES.txt
FreeSpeech.egg-info/dependency_links.txt
FreeSpeech.egg-info/requires.txt
FreeSpeech.egg-info/top_level.txt