Metadata-Version: 1.1
Name: FreeSpeech
Version: 0.1
Summary: It creates random speach.
Home-page: https://github.com/equidna/FreeSpeech
Author: Rui Lima
Author-email: ruirochalima1@gmail.com
License: GPLv2
Download-URL: https://github.com/equidna/FreeSpeech/tarball/0.1
Keywords: fake,content,creation
Platform: UNKNOWN
Classifier: Environment :: Console
Classifier: Development Status :: 4 - Beta
Classifier: Intended Audience :: Science/Research
Classifier: Programming Language :: Python
Classifier: Programming Language :: Python :: 2.7
